setup.py
leo_dens_distributions/Binomialdistribution.py
leo_dens_distributions/Gaussiandistribution.py
leo_dens_distributions/Generaldistribution.py
leo_dens_distributions/__init__.py
leo_dens_distributions.egg-info/PKG-INFO
leo_dens_distributions.egg-info/SOURCES.txt
leo_dens_distributions.egg-info/dependency_links.txt
leo_dens_distributions.egg-info/not-zip-safe
leo_dens_distributions.egg-info/top_level.txt