Metadata-Version: 1.0
Name: leo-dens-distributions
Version: 0.2
Summary: Gaussian distributions
Home-page: UNKNOWN
Author: Leonardo Soares
Author-email: UNKNOWN
License: UNKNOWN
Platform: UNKNOWN
